curiosity/__init__.py
curiosity/edge.py
curiosity/graph.py
curiosity/graph_operation.py
curiosity/helpers.py
curiosity/node.py
curiosity/endpoints/__init__.py
curiosity/endpoints/library.py
curiosity/mosaik/__init__.py
curiosity/mosaik/core/__init__.py
curiosity/mosaik/core/languages.py
curiosity/query/__init__.py
curiosity/query/query.py
curiosity/query/query_result.py
curiosity-54593.dist-info/METADATA
curiosity-54593.dist-info/WHEEL
curiosity-54593.dist-info/top_level.txt
curiosity-54593.dist-info/RECORD
