Metadata-Version: 2.1
Name: curiosity
Version: 54593
Summary: The official Python driver for the Curiosity Search engine (https://curiosity.ai/).
Home-page: http://curiosity.ai
Author: curiosity.ai
Author-email: hello@curiosity.ai
License: UNKNOWN
Platform: UNKNOWN
Requires-Dist: requests>=2.25.0
Requires-Dist: urllib3>=1.26.2
